magic_lamp.py
magic_lamp-0.4.1.dist-info/LICENSE
magic_lamp-0.4.1.dist-info/METADATA
magic_lamp-0.4.1.dist-info/WHEEL
magic_lamp-0.4.1.dist-info/RECORD
