Metadata-Version: 2.1
Name: magic-lamp
Version: 0.4.1
Summary: Easily integrate LLMs into Python code.
Home-page: https://github.com/rameshvarun/magic-lamp
License: MIT
Author: Varun Ramesh
Author-email: varunramesh@live.com
Requires-Python: >=3.9,<4.0
Classifier: License :: OSI Approved :: MIT License
Classifier: Programming Language :: Python :: 3
Classifier: Programming Language :: Python :: 3.9
Classifier: Programming Language :: Python :: 3.10
Classifier: Programming Language :: Python :: 3.11
Classifier: Programming Language :: Python :: 3.12
Requires-Dist: huggingface-hub (>=0.24.5,<0.25.0)
Requires-Dist: llama-cpp-python (>=0.2.85,<0.3.0)
Project-URL: Repository, https://github.com/rameshvarun/magic-lamp
